odoo8_addon_auditlog-8.0.2.1.0-nspkg.pth
odoo_addons/auditlog/README.rst
odoo_addons/auditlog/__init__.py
odoo_addons/auditlog/__openerp__.py
odoo_addons/auditlog/data/ir_cron.xml
odoo_addons/auditlog/i18n/am.po
odoo_addons/auditlog/i18n/ar.po
odoo_addons/auditlog/i18n/auditlog.pot
odoo_addons/auditlog/i18n/bg.po
odoo_addons/auditlog/i18n/bs.po
odoo_addons/auditlog/i18n/ca.po
odoo_addons/auditlog/i18n/ca_ES.po
odoo_addons/auditlog/i18n/cs.po
odoo_addons/auditlog/i18n/da.po
odoo_addons/auditlog/i18n/da_DK.po
odoo_addons/auditlog/i18n/de.po
odoo_addons/auditlog/i18n/el_GR.po
odoo_addons/auditlog/i18n/en_GB.po
odoo_addons/auditlog/i18n/es.po
odoo_addons/auditlog/i18n/es_AR.po
odoo_addons/auditlog/i18n/es_CL.po
odoo_addons/auditlog/i18n/es_CO.po
odoo_addons/auditlog/i18n/es_CR.po
odoo_addons/auditlog/i18n/es_DO.po
odoo_addons/auditlog/i18n/es_EC.po
odoo_addons/auditlog/i18n/es_ES.po
odoo_addons/auditlog/i18n/es_MX.po
odoo_addons/auditlog/i18n/es_PE.po
odoo_addons/auditlog/i18n/es_PY.po
odoo_addons/auditlog/i18n/es_VE.po
odoo_addons/auditlog/i18n/et.po
odoo_addons/auditlog/i18n/eu.po
odoo_addons/auditlog/i18n/fa.po
odoo_addons/auditlog/i18n/fi.po
odoo_addons/auditlog/i18n/fr.po
odoo_addons/auditlog/i18n/fr_CA.po
odoo_addons/auditlog/i18n/fr_CH.po
odoo_addons/auditlog/i18n/fr_FR.po
odoo_addons/auditlog/i18n/gl.po
odoo_addons/auditlog/i18n/gl_ES.po
odoo_addons/auditlog/i18n/he.po
odoo_addons/auditlog/i18n/hr.po
odoo_addons/auditlog/i18n/hr_HR.po
odoo_addons/auditlog/i18n/hu.po
odoo_addons/auditlog/i18n/id.po
odoo_addons/auditlog/i18n/it.po
odoo_addons/auditlog/i18n/ja.po
odoo_addons/auditlog/i18n/ko.po
odoo_addons/auditlog/i18n/lt.po
odoo_addons/auditlog/i18n/lt_LT.po
odoo_addons/auditlog/i18n/lv.po
odoo_addons/auditlog/i18n/mk.po
odoo_addons/auditlog/i18n/mn.po
odoo_addons/auditlog/i18n/nb.po
odoo_addons/auditlog/i18n/nb_NO.po
odoo_addons/auditlog/i18n/nl.po
odoo_addons/auditlog/i18n/nl_BE.po
odoo_addons/auditlog/i18n/nl_NL.po
odoo_addons/auditlog/i18n/pl.po
odoo8_addon_auditlog-8.0.2.1.0.dist-info/METADATA
odoo8_addon_auditlog-8.0.2.1.0.dist-info/WHEEL
odoo8_addon_auditlog-8.0.2.1.0.dist-info/namespace_packages.txt
odoo8_addon_auditlog-8.0.2.1.0.dist-info/top_level.txt
odoo8_addon_auditlog-8.0.2.1.0.dist-info/RECORD
